mocker_builder/__init__.py
mocker_builder/mocker_builder.py
mocker_builder-0.2.0.dist-info/LICENSE.md
mocker_builder-0.2.0.dist-info/METADATA
mocker_builder-0.2.0.dist-info/WHEEL
mocker_builder-0.2.0.dist-info/top_level.txt
mocker_builder-0.2.0.dist-info/RECORD
