Metadata-Version: 2.1
Name: mocker-builder
Version: 0.2.0
Summary: Python library to build mock tests dynamicaly using the mocker feature from pytest-mock lib
Home-page: https://github.com/tgc77/mocker_builder
Author: Tiago G Cunha
Author-email: tikx.batera@gmail.com
License: MIT
Project-URL: Documentation, https://mocker-builder.readthedocs.io
Project-URL: Source, https://github.com/tgc77/mocker_builder
Keywords: pytest mock mocker
Platform: UNKNOWN
Classifier: Intended Audience :: Developers
Classifier: License :: OSI Approved :: MIT License
Classifier: Programming Language :: Python
Classifier: Programming Language :: Python :: 3
Classifier: Programming Language :: Python :: 3.6
Classifier: Programming Language :: Python :: 3.7
Classifier: Programming Language :: Python :: 3.8
Classifier: Programming Language :: Python :: 3.9
Classifier: Operating System :: OS Independent
Requires-Dist: pytest (==7.1.3)
Requires-Dist: pytest-mock (==3.8.2)
Requires-Dist: mock (==4.0.3)
